[{"id":"02faf01c-adc0-41dd-93cc-492250f07bc0","user":"Yeah","text":"Amazing!","added":"2024-08-04T01:03:36.823Z"},{"id":"3d9a3b5c-b1cd-489f-942b-d6f6ac8d5375","user":"Yeah","text":"Yeah!","added":"2024-08-04T01:02:56.456Z"},{"id":"3ad1a307-6997-4a04-bccf-b9b38f8cc151","user":"Test","text":"@@@@@@@@@@@@@@@@@@@@@@@@@@@@@@@@@@@@@@@@@@@@@@@@@@@@@@@@@@@@@@@@@@@@@@@@@@@@@@@@@@@@@@@@@@@@@@@@@@@@@@@@@@@@@@@@@@@@@@@@@@@@@@@@@@@@@@@@@@@@@@@@@@@@@@@@@@@@@@@@@@@@@@@@@@@@@@@@@@@@@@@@@@@@@@@@@@@@@@@@@@@@@@@@@@@@@@@@@@@@@@@@@@@@@@@@@@@@@@@@@@@@@@@@@@@@@@@","added":"2024-08-04T00:58:29.286Z"},{"id":"bd1a52a6-0937-4e63-bf1e-097a12c12f75","user":"Test","text":"@@@@@@@@@@@@@@@@@@@@@@@@@@@@@@@@@@@@@@@@@@@@@@@@@@@@@@@@@@@@@@@@@@@@@@@@@@@@@@@@@@@@@@@@@@@@@@@@@@@@@@@@@@@@@@@@@@@@@@@@@@@@@@@@@@@@@@@@@@@@@@@@@@@@@@@@@@@@@@@@@@@@@@@@@@@@@@@@@@@@@@@@@@@@@@@@@@@@@@@@@@@@@@@@@@@@@@@@@@@@@@@@@@@@@@@@@@@@@@@@@@@@@@@@@@@@@@@","added":"2024-08-04T00:58:29.283Z"},{"id":"6d67a2cc-6b96-4425-b13f-eedd2b10742a","user":"Test","text":"@@@@@@@@@@@@@@@@@@@@@@@@@@@@@@@@@@@@@@@@@@@@@@@@@@@@@@@@@@@@@@@@@@@@@@@@@@@@@@@@@@@@@@@@@@@@@@@@@@@@@@@@@@@@@@@@@@@@@@@@@@@@@@@@@@@@@@@@@@@@@@@@@@@@@@@@@@@@@@@@@@@@@@@@@@@@@@@@@@@@@@@@@@@@@@@@@@@@@@@@@@@@@@@@@@@@@@@@@@@@@@@@@@@@@@@@@@@@@@@@@@@@@@@@@@@@@@@","added":"2024-08-04T00:58:29.275Z"},{"id":"68b178bc-1c02-434a-aacc-d0af104df3bc","user":"Test","text":"@@@@@@@@@@@@@@@@@@@@@@@@@@@@@@@@@@@@@@@@@@@@@@@@@@@@@@@@@@@@@@@@@@@@@@@@@@@@@@@@@@@@@@@@@@@@@@@@@@@@@@@@@@@@@@@@@@@@@@@@@@@@@@@@@@@@@@@@@@@@@@@@@@@@@@@@@@@@@@@@@@@@@@@@@@@@@@@@@@@@@@@@@@@@@@@@@@@@@@@@@@@@@@@@@@@@@@@@@@@@@@@@@@@@@@@@@@@@@@@@@@@@@@@@@@@@@@@","added":"2024-08-04T00:58:28.004Z"},{"id":"6e9aa298-35b2-4484-9755-2f45666ca933","user":"Test","text":"@@@@@@@@@@@@@@@@@@@@@@@@@@@@@@@@@@@@@@@@@@@@@@@@@@@@@@@@@@@@@@@@@@@@@@@@@@@@@@@@@@@@@@@@@@@@@@@@@@@@@@@@@@@@@@@@@@@@@@@@@@@@@@@@@@@@@@@@@@@@@@@@@@@@@@@@@@@@@@@@@@@@@@@@@@@@@@@@@@@@@@@@@@@@@@@@@@@@@@@@@@@@@@@@@@@@@@@@@@@@@@@@@@@@@@@@@@@@@@@@@@@@@@@@@@@@@@@","added":"2024-08-04T00:58:26.809Z"},{"id":"131259c2-c443-4c10-a83c-49d30428fbb5","user":"Test","text":"@@@@@@@@@@@@@@@@@@@@@@@@@@@@@@@@@@@@@@@@@@@@@@@@@@@@@@@@@@@@@@@@@@@@@@@@@@@@@@@@@@@@@@@@@@@@@@@@@@@@@@@@@@@@@@@@@@@@@@@@@@@@@@@@@@@@@@@@@@@@@@@@@@@@@@@@@@@@@@@@@@@@@@@@@@@@@@@@@@@@@@@@@@@@@@@@@@@@@@@@@@@@@@@@@@@@@@@@@@@@@@@@@@@@@@@@@@@@@@@@@@@@@@@@@@@@@@@","added":"2024-08-04T00:58:26.803Z"},{"id":"82bef7bf-8d59-4df2-bacb-677a70d5b09e","user":"Test","text":"@@@@@@@@@@@@@@@@@@@@@@@@@@@@@@@@@@@@@@@@@@@@@@@@@@@@@@@@@@@@@@@@@@@@@@@@@@@@@@@@@@@@@@@@@@@@@@@@@@@@@@@@@@@@@@@@@@@@@@@@@@@@@@@@@@@@@@@@@@@@@@@@@@@@@@@@@@@@@@@@@@@@@@@@@@@@@@@@@@@@@@@@@@@@@@@@@@@@@@@@@@@@@@@@@@@@@@@@@@@@@@@@@@@@@@@@@@@@@@@@@@@@@@@@@@@@@@@","added":"2024-08-04T00:58:25.595Z"},{"id":"61fa8c88-4184-4be6-b8a0-aa361144a80e","user":"Test","text":"@@@@@@@@@@@@@@@@@@@@@@@@@@@@@@@@@@@@@@@@@@@@@@@@@@@@@@@@@@@@@@@@@@@@@@@@@@@@@@@@@@@@@@@@@@@@@@@@@@@@@@@@@@@@@@@@@@@@@@@@@@@@@@@@@@@@@@@@@@@@@@@@@@@@@@@@@@@@@@@@@@@@@@@@@@@@@@@@@@@@@@@@@@@@@@@@@@@@@@@@@@@@@@@@@@@@@@@@@@@@@@@@@@@@@@@@@@@@@@@@@@@@@@@@@@@@@@@","added":"2024-08-04T00:58:23.675Z"},{"id":"1ecf6b67-1eab-4c99-a43c-b6ddaa6c878b","user":"David","text":"AOKDpAKWDopAWKD","added":"2024-08-04T00:40:53.277Z"},{"id":"11e09ed3-71ed-4bd5-82bf-e0379f56ad36","user":"Crazy","text":"xDDDDDDD","added":"2024-08-04T00:39:50.784Z"},{"id":"6ef8af94-b998-42e1-9f8c-15f87319457e","user":"David","text":"Let's add some new features!","added":"2024-08-04T00:39:30.326Z"},{"id":"3d751c18-a498-4d6f-9c8a-d2e0d1c2a6c1","user":"David","text":"It might be my best website!","added":"2024-08-04T00:39:16.172Z"},{"id":"91173cfc-5fb2-46ba-9596-0eebf8ca2c52","user":"David","text":"Animations!","added":"2024-08-04T00:05:49.278Z"},{"id":"7919bb62-8ba9-4792-a1d8-3f229e052d2a","user":"David","text":"What?","added":"2024-08-03T23:55:00.898Z"},{"id":"dcb3f718-a732-4b4f-b232-c6357319a7b7","user":"David","text":"It does!","added":"2024-08-03T23:45:06.757Z"},{"id":"1fff7433-4cde-46f1-9aba-37de65040615","user":"David","text":"Does it work?","added":"2024-08-03T23:44:52.265Z"},{"id":"bcc5f9a8-e351-4174-accb-1647b95c0c30","user":"David","text":"X X X X X X X X X X X X X X X X X X X X X X X X X X X X X X X X X X X X X X X X X X X X X X X X X X X X X X X X X X X X X X X X X X X X X X X X X X X X X X X X X X X X X X X X X X X X X X X X X X X X X v","added":"2024-08-03T23:03:47.592Z"},{"id":"b2c72723-7f34-40e0-b2ee-7a2972f783ce","user":"David","text":"@@@@@@@@@@@@@@@@@@@@@@@@@@@@@@@@@@@@@@@@@@@@@@@@@@@@@@@@@@@@@@@@@@@@@@@@@@@@@@@@@@@@@@@@@@@@@@@@@@@@@@@@@@@@@@@@@@@@@@@@@@@@@@@@@@@@@@@@@@@@@@@@@@@@@@@@@@@@@@@@@@@@@@@@@@@@@@@@@@@@@@@@@@@@@@@@@@@@@@@@@@@@@@@@@@@@@@@@@@@@@@@@@@@@@@@@@@@@@@@@@@@@@@@@@@@@v","added":"2024-08-03T22:49:54.613Z"},{"id":"7a0edfb4-95e8-4b03-b64c-788e8f9bee1f","user":"Bartek","text":"Amazing!","added":"2024-08-03T22:40:52.274Z"},{"id":"1c769e8a-a4cc-48f1-bfb5-f03c60363f88","user":"David","text":"Crazy!","added":"2024-08-03T22:39:31.655Z"}]